cforma/__init__.py
cforma/cf.py
cforma-0.1.2.dist-info/licenses/LICENSE
cforma-0.1.2.dist-info/METADATA
cforma-0.1.2.dist-info/WHEEL
cforma-0.1.2.dist-info/top_level.txt
cforma-0.1.2.dist-info/RECORD
