Metadata-Version: 2.4
Name: cforma
Version: 0.1.2
Summary: A utility to format Pydantic models into clean JSON Schemas for LLMs.
Author-email: Grace Peter Mutiibwa <temporarybag.grace@gmail.com>
License: Copyright 2025 GRACE PETER MUTIIBWA
Project-URL: Homepage, https://github.com/GracePeterMutiibwa/cforma
Classifier: Programming Language :: Python :: 3
Classifier: License :: OSI Approved :: MIT License
Classifier: Operating System :: OS Independent
Classifier: Development Status :: 4 - Beta
Classifier: Intended Audience :: Developers
Classifier: Topic :: Software Development :: Libraries :: Python Modules
Classifier: Topic :: Utilities
Requires-Python: >=3.8
License-File: LICENSE
Requires-Dist: pydantic
Dynamic: license-file
